termslides/__init__.py
termslides/effects.py
termslides/renderers.py
termslides/termslides.py
termslides/widgets.py
termslides/lib/plantuml.1.2021.9.jar
tests/__init__.py
tests/test_import.py
termslides-1.10.dist-info/LICENSE
termslides-1.10.dist-info/METADATA
termslides-1.10.dist-info/WHEEL
termslides-1.10.dist-info/entry_points.txt
termslides-1.10.dist-info/top_level.txt
termslides-1.10.dist-info/RECORD
