Metadata-Version: 2.1
Name: termslides
Version: 1.10
Summary: Script your slides in YAML file and show it in terminal.
Home-page: https://github.com/onelife/termslides
Author: onelife
Author-email: onelife.real@gmail.com
License: Apache-2.0
Download-URL: https://github.com/onelife/termslides/archive/1.10.tar.gz
Keywords: terminal,slides,asscii,art
Platform: UNKNOWN
Classifier: Environment :: Console
Classifier: License :: OSI Approved :: Apache Software License
Classifier: Natural Language :: English
Classifier: Operating System :: Microsoft :: Windows
Classifier: Operating System :: POSIX :: Linux
Classifier: Programming Language :: Python :: 3
Classifier: Topic :: Text Processing :: Markup
Requires-Dist: pyyaml (==5.*)
Requires-Dist: asciimatics (==1.*)
Requires-Dist: tabulate (==0.*)
Requires-Dist: plantuml (==0.*)
Requires-Dist: tqdm (==4.*)
Requires-Dist: click (==7.*)
